amaptor/__init__.py
amaptor/constants.py
amaptor/errors.py
amaptor/functions.py
amaptor/version.py
amaptor/version_check.py
amaptor/classes/__init__.py
amaptor/classes/__init__.pyc
amaptor/classes/layer.py
amaptor/classes/layer.pyc
amaptor/classes/layout.py
amaptor/classes/layout.pyc
amaptor/classes/map.py
amaptor/classes/map.pyc
amaptor/classes/map_frame.py
amaptor/classes/map_frame.pyc
amaptor/classes/project.py
amaptor/classes/project.pyc
amaptor/classes/__pycache__/__init__.cpython-34.pyc
amaptor/classes/__pycache__/__init__.cpython-35.pyc
amaptor/classes/__pycache__/layer.cpython-35.pyc
amaptor/classes/__pycache__/layout.cpython-34.pyc
amaptor/classes/__pycache__/layout.cpython-35.pyc
amaptor/classes/__pycache__/map.cpython-34.pyc
amaptor/classes/__pycache__/map.cpython-35.pyc
amaptor/classes/__pycache__/map_frame.cpython-34.pyc
amaptor/classes/__pycache__/map_frame.cpython-35.pyc
amaptor/classes/__pycache__/project.cpython-34.pyc
amaptor/classes/__pycache__/project.cpython-35.pyc
amaptor/templates/arcmap/pro_import_map_template.mxd
amaptor/templates/pro/blank_layer.lyr
amaptor/templates/pro/blank_layout.pagx
amaptor/templates/pro/blank_raster_layer.lyr
amaptor/templates/pro/blank_pro_project/blank_pro_project.aprx
amaptor/templates/pro/blank_pro_project/blank_pro_project.tbx
amaptor/templates/pro/blank_pro_project/blank_pro_project.gdb/a00000001.TablesByName.atx
amaptor/templates/pro/blank_pro_project/blank_pro_project.gdb/a00000001.gdbindexes
amaptor/templates/pro/blank_pro_project/blank_pro_project.gdb/a00000001.gdbtable
amaptor/templates/pro/blank_pro_project/blank_pro_project.gdb/a00000001.gdbtablx
amaptor/templates/pro/blank_pro_project/blank_pro_project.gdb/a00000002.gdbtable
amaptor/templates/pro/blank_pro_project/blank_pro_project.gdb/a00000002.gdbtablx
amaptor/templates/pro/blank_pro_project/blank_pro_project.gdb/a00000003.gdbindexes
amaptor-0.1.2.3.dist-info/DESCRIPTION.rst
amaptor-0.1.2.3.dist-info/METADATA
amaptor-0.1.2.3.dist-info/RECORD
amaptor-0.1.2.3.dist-info/WHEEL
amaptor-0.1.2.3.dist-info/metadata.json
amaptor-0.1.2.3.dist-info/top_level.txt
