Metadata-Version: 2.0
Name: amaptor
Version: 0.1.2.3
Summary: A compatibility layer (or adaptor) for mapping functions in ArcGIS 10.x (arcpy.mapping/Python 2) and ArcGIS Pro (arcpy.mp/Python 3)
Home-page: https://github.com/ucd-cws/amaptor
Author: nickrsan
Author-email: nrsantos@ucdavis.edu
License: UNKNOWN
Platform: UNKNOWN
Requires: arcpy
